umlizer/__init__.py
umlizer/__main__.py
umlizer/class_graph.py
umlizer/cli.py
umlizer/py.typed
umlizer-0.1.1.dist-info/LICENSE
umlizer-0.1.1.dist-info/METADATA
umlizer-0.1.1.dist-info/WHEEL
umlizer-0.1.1.dist-info/entry_points.txt
umlizer-0.1.1.dist-info/RECORD
